{
  "button": {
    "color": {
      "background": {
        "default": {
          "value": "{color.neutral.white}"
        },
        "hover": {
          "value": "{color.neutral.white}"
        },
        "active": {
          "value": "{color.neutral.white}"
        },
        "disabled": {
          "value": "{color.neutral.white}"
        }
      },
      "content": {
        "default": {
          "value": "{color.brand.pink.700}"
        },
        "hover": {
          "value": "{color.brand.pink.800}"
        },
        "active": {
          "value": "{color.brand.pink.800}"
        },
        "disabled": {
          "value": "{color.brand.pink.100}"
        }
      },
      "border": {
        "default": {
          "value": "{color.brand.pink.700}"
        },
        "hover": {
          "value": "{color.brand.pink.800}"
        },
        "active": {
          "value": "{color.brand.pink.800}"
        },
        "disabled": {
          "value": "{color.brand.pink.100}"
        }
      }
    },
    "primary": {
      "color": {
        "background": {
          "default": {
            "value": "{color.brand.pink.700}"
          },
          "hover": {
            "value": "{color.brand.pink.800}"
          },
          "active": {
            "value": "{color.brand.pink.800}"
          },
          "disabled": {
            "value": "{color.brand.pink.100}"
          }
        },
        "content": {
          "default": {
            "value": "{color.neutral.white}"
          },
          "hover": {
            "value": "{color.neutral.white}"
          },
          "active": {
            "value": "{color.neutral.white}"
          },
          "disabled": {
            "value": "{color.neutral.white}"
          }
        },
        "border": {
          "default": {
            "value": "{color.brand.pink.700}"
          },
          "hover": {
            "value": "{color.brand.pink.800}"
          },
          "active": {
            "value": "{color.brand.pink.800}"
          },
          "disabled": {
            "value": "{color.brand.pink.100}"
          }
        }
      }
    }
  }
}
